FibDB-0.1.1.2.dist-info/DESCRIPTION.rst
FibDB-0.1.1.2.dist-info/METADATA
FibDB-0.1.1.2.dist-info/RECORD
FibDB-0.1.1.2.dist-info/WHEEL
FibDB-0.1.1.2.dist-info/metadata.json
FibDB-0.1.1.2.dist-info/top_level.txt
fibdb/__init__.py
