Metadata-Version: 2.0
Name: FibDB
Version: 0.1.1.2
Summary: Efficienct generation and storage of Fibonacci numbers,1000x faster than Hadoop
Home-page: https://github.com/ivanov/fibdb
Author: Paul Ivanov
Author-email: pi@berkeley.edu
License: BSD
Platform: UNKNOWN
